odoo/addons/bookstore_mgmt/README.rst
odoo/addons/bookstore_mgmt/__init__.py
odoo/addons/bookstore_mgmt/__manifest__.py
odoo/addons/bookstore_mgmt/i18n/bookstore_mgmt.pot
odoo/addons/bookstore_mgmt/i18n/ca.po
odoo/addons/bookstore_mgmt/i18n/es.po
odoo/addons/bookstore_mgmt/i18n/it.po
odoo/addons/bookstore_mgmt/models/__init__.py
odoo/addons/bookstore_mgmt/models/product_template.py
odoo/addons/bookstore_mgmt/readme/CONTRIBUTORS.md
odoo/addons/bookstore_mgmt/readme/DESCRIPTION.md
odoo/addons/bookstore_mgmt/security/bookstore_security.xml
odoo/addons/bookstore_mgmt/security/ir.model.access.csv
odoo/addons/bookstore_mgmt/static/description/icon.png
odoo/addons/bookstore_mgmt/static/description/index.html
odoo/addons/bookstore_mgmt/views/bookstore_mgmt.xml
odoo/addons/bookstore_mgmt/views/product.xml
odoo_addon_bookstore_mgmt-17.0.3.0.0.2.dist-info/METADATA
odoo_addon_bookstore_mgmt-17.0.3.0.0.2.dist-info/WHEEL
odoo_addon_bookstore_mgmt-17.0.3.0.0.2.dist-info/top_level.txt
odoo_addon_bookstore_mgmt-17.0.3.0.0.2.dist-info/RECORD
